travel_units_converter/__init__.py
travel_units_converter/main.py
travel_units_converter-0.1.0.dist-info/METADATA
travel_units_converter-0.1.0.dist-info/WHEEL
travel_units_converter-0.1.0.dist-info/RECORD
